airflow_clickhouse_plug/hooks/clickhouse.py
airflow_clickhouse_plug/hooks/clickhouse_dbapi.py
airflow_clickhouse_plug/operators/clickhouse.py
airflow_clickhouse_plug/operators/clickhouse_dbapi.py
airflow_clickhouse_plug/sensors/clickhouse.py
airflow_clickhouse_plug/sensors/clickhouse_dbapi.py
airflow_clickhouse_plug-1.6.2.dist-info/licenses/LICENSE
airflow_clickhouse_plug-1.6.2.dist-info/METADATA
airflow_clickhouse_plug-1.6.2.dist-info/WHEEL
airflow_clickhouse_plug-1.6.2.dist-info/top_level.txt
airflow_clickhouse_plug-1.6.2.dist-info/RECORD
