Metadata-Version: 2.4
Name: airflow-clickhouse-plug
Version: 1.6.2
Summary: airflow-clickhouse-plug — Airflow plugin to execute ClickHouse commands and queries
Author-email: Firstname Secondname <xxx.xxxx@gmail.com>
License: MIT License
Project-URL: GitHub, https://github.com/StashOfCode/airflow-clickhouse-plug
Project-URL: Documentation, https://github.com/StashOfCode/airflow-clickhouse-plug#airflow-clickhouse-plug
Project-URL: Changelog, https://github.com/StashOfCode/airflow-clickhouse-plug/releases
Project-URL: Issues, https://github.com/StashOfCode/airflow-clickhouse-plug/issues
Keywords: clickhouse,airflow
Classifier: Development Status :: 5 - Production/Stable
Classifier: Environment :: Plugins
Classifier: Intended Audience :: Developers
Classifier: Programming Language :: Python :: 3.12
Classifier: Programming Language :: Python :: 3.11
Classifier: Programming Language :: Python :: 3.10
Classifier: Programming Language :: Python :: 3.9
Requires-Python: >=3.9
License-File: LICENSE
Requires-Dist: clickhouse-driver~=0.2.9
Requires-Dist: apache-airflow<3.2.0,>=2.0.0
Provides-Extra: common-sql
Requires-Dist: apache-airflow[common.sql]<3.2.0,>=2.2.0; extra == "common-sql"
Requires-Dist: apache-airflow-providers-common-sql>=1.3.0; extra == "common-sql"
Requires-Dist: clickhouse-driver>=0.2.1; extra == "common-sql"
Dynamic: license-file
